setup.py
resn/__init__.py
resn.egg-info/PKG-INFO
resn.egg-info/SOURCES.txt
resn.egg-info/dependency_links.txt
resn.egg-info/top_level.txt