Metadata-Version: 1.0
Name: resn
Version: 0.1
Summary: resn (REdis Social Network) is a simple library to create social networks. It provides a backend for data models using Redis, supporting friends, followers, updates and a news feed out of the box.
Home-page: http://github.com/vivekn/resn
Author: Vivek.Narayanan
Author-email: mail@vivekn.co.cc
License: BSD
Keywords: redis,social network
Platform: Any
Classifier: Development Status :: 4 - Beta
Classifier: Intended Audience :: Developers
Classifier: License :: OSI Approved :: BSD License
Classifier: Operating System :: OS Independent
Classifier: Programming Language :: Python
Classifier: Topic :: Software Development :: Libraries :: Python Modules
